BlazeSudio/BlazeSudio
BlazeSudio/__init__.py
BlazeSudio/Game/__init__.py
BlazeSudio/Game/player.py
BlazeSudio/Game/statics.py
BlazeSudio/Game/world.py
BlazeSudio/collisions/__init__.py
BlazeSudio/collisions/collisions.cp310-win_amd64.pyd
BlazeSudio/collisions/collisions.cp311-win_amd64.pyd
BlazeSudio/collisions/collisions.cp312-win_amd64.pyd
BlazeSudio/collisions/collisions.cpython-310-x86_64-linux-gnu.so
BlazeSudio/collisions/collisions.cpython-311-x86_64-linux-gnu.so
BlazeSudio/collisions/collisions.cpython-312-x86_64-linux-gnu.so
BlazeSudio/collisions/setup.py
BlazeSudio/collisions/lib/__init__.py
BlazeSudio/collisions/lib/collisions.py
BlazeSudio/elementGen/__init__.py
BlazeSudio/elementGen/node_editor.py
BlazeSudio/elementGen/node_parser.py
BlazeSudio/elementGen/types.py
BlazeSudio/graphics/__init__.py
BlazeSudio/graphics/graphics.py
BlazeSudio/graphics/loading.py
BlazeSudio/graphics/options.py
BlazeSudio/graphics/stacks.py
BlazeSudio/graphics/stuff.py
BlazeSudio/graphics/GUI/__init__.py
BlazeSudio/graphics/GUI/colourpick.py
BlazeSudio/graphics/GUI/elements.py
BlazeSudio/graphics/GUI/events.py
BlazeSudio/graphics/GUI/pyguix/__init__.py
BlazeSudio/graphics/GUI/pyguix/utils.py
BlazeSudio/graphics/GUI/pyguix/ui/__init__.py
BlazeSudio/graphics/GUI/pyguix/ui/elements.py
BlazeSudio/graphics/GUI/pyguix/ui/context/__init__.py
BlazeSudio/graphics/GUI/pyguix/ui/settings/__init__.py
BlazeSudio/graphics/GUI/pyguix/ui/themes/__init__.py
BlazeSudio/graphics/GUI/textboxify/__init__.py
BlazeSudio/graphics/GUI/textboxify/borders.py
BlazeSudio/graphics/GUI/textboxify/settings.py
BlazeSudio/graphics/GUI/textboxify/textbox.py
BlazeSudio/graphics/GUI/textboxify/util.py
BlazeSudio/ldtk/Pyldtk.py
BlazeSudio/ldtk/__init__.py
BlazeSudio/ldtk/application.py
BlazeSudio/ldtk/sync.py
BlazeSudio/worldGen/__init__.py
BlazeSudio/worldGen/terrainGen.py
BlazeSudio/worldGen/world.py
Blaze_Sudio-3.0.1.data/scripts/BlazeSudio
Blaze_Sudio-3.0.1.dist-info/LICENSE
Blaze_Sudio-3.0.1.dist-info/METADATA
Blaze_Sudio-3.0.1.dist-info/WHEEL
Blaze_Sudio-3.0.1.dist-info/top_level.txt
Blaze_Sudio-3.0.1.dist-info/RECORD
