Metadata-Version: 2.1
Name: Blaze-Sudio
Version: 3.0.1
Summary: This is the really cool game engine!
Home-page: https://github.com/Tsunami014/Blaze-Sudio
Download-URL: https://github.com/Tsunami014/Blaze-Sudio/archive/refs/tags/v3.0.1.tar.gz
Author: Tsunami014 (Max)
Author-email: tsunami014@duck.com
License: Apache
Keywords: Python,games,engine
Classifier: Development Status :: 5 - Production/Stable
Classifier: Intended Audience :: Developers
Classifier: Programming Language :: Python :: 3
Classifier: Topic :: Software Development :: Build Tools
Classifier: Operating System :: Unix
Classifier: Operating System :: Microsoft :: Windows
License-File: LICENSE
Requires-Dist: pygame
Requires-Dist: nPerlinNoise
Requires-Dist: scikit-image
Requires-Dist: matplotlib
Requires-Dist: pyperclip
Requires-Dist: shapely
